scSplit/__init__.py
scSplit/scSplit
scSplit-1.0.8.2.dist-info/LICENSE.txt
scSplit-1.0.8.2.dist-info/METADATA
scSplit-1.0.8.2.dist-info/WHEEL
scSplit-1.0.8.2.dist-info/top_level.txt
scSplit-1.0.8.2.dist-info/RECORD
