Metadata-Version: 2.1
Name: scSplit
Version: 1.0.8.2
Summary: Genotype-free demultiplexing of pooled single-cell RNA-Seq
Home-page: https://github.com/jon-xu/scSplit
Author: Jun Xu
Author-email: jun.xu@uq.edu.au
License: UNKNOWN
Download-URL: https://github.com/jon-xu/scSplit/archive/refs/tags/v1.0.8.tar.gz
Platform: UNKNOWN
Classifier: Programming Language :: Python :: 3
Classifier: License :: OSI Approved :: MIT License
Classifier: Operating System :: OS Independent
